sodisys/__init__.py
sodisys/auth.py
sodisys/py.typed
sodisys/sodisys.py
sodisys/cli/__init__.py
sodisys/cli/commands.py
sodisys/rest_api/__init__.py
sodisys/rest_api/model/data.py
sodisys/rest_api/model/live.py
sodisys-0.5.0.dist-info/METADATA
sodisys-0.5.0.dist-info/WHEEL
sodisys-0.5.0.dist-info/entry_points.txt
sodisys-0.5.0.dist-info/RECORD
