Metadata-Version: 2.4
Name: sodisys
Version: 0.5.0
Summary: Add your description here
Author-email: Sebastian Rutofski <kontakt@sebastian-rutofski.de>
Requires-Python: >=3.12
Requires-Dist: aiohttp>=3.11.18
Requires-Dist: asyncio>=3.4.3
Requires-Dist: pydantic>=2.11.7
Provides-Extra: cli
Requires-Dist: asyncclick~=8.1; extra == 'cli'
Requires-Dist: coloredlogs~=15.0; extra == 'cli'
Requires-Dist: pygments~=2.18; extra == 'cli'
Requires-Dist: rich>=14.1.0; extra == 'cli'
Requires-Dist: termcolor~=3.0; extra == 'cli'
